{ 
  "esqueleto": {
    "name": "esqueleto",
    "hostile": false,
    "s": {"x": 3, "y": 3},
    "frame_positions": {"walking": {"i":2, "f":7, "type": "default"}},
    "type":"walking",
    "direction": 1,
    "body": {"w":20, "h":20}
  },
  "lobo": {
    "name": "lobo",
    "hostile": {
      "damage": 1,
      "attack_frame": 23
    },
    "s": {"x": 0.75, "y": 0.75},
    "frame_positions": {
      "walking": {"i":4, "f":7, "type": "default"},
      "attacking": {"i":19, "f":26, "type": "until_finished"},
      "dying": {"i": 27, "f": 33, "type": "until_finished", "audio": "lobo_dying.mp3"}
    },
    "type":"walking",
    "direction": -1,
    "body": {"w":150, "h":120}
  },
  "owl": {
    "name": "owl",
    "hostile": {
      "damage": 1,
      "attack_frame": [33, 34, 35, 36, 37, 38, 39, 40, 41, 42, 43, 44, 45, 46, 47, 48]
    },
    "s": {"x": 3, "y": 3},
    "frame_positions": {
      "flying": {"i": 17, "f": 32, "type": "default"}
    },
    "type":"flying",
    "direction": -1,
    "body": {"w":40, "h":20}
  },
  "bat": {
    "name": "bat",
    "hostile": {
      "damage": 1,
      "attack_frame": [1, 2, 3, 4, 5, 6]
    },
    "s": {"x": 3, "y": 3},
    "frame_positions": {
      "flying": {"i": 1, "f": 5, "type": "default"}
    },
    "type":"flying",
    "direction": -1,
    "body": {"w":40, "h":20}
  }
}